odoo/addons/sale_elaboration_weighing/README.rst
odoo/addons/sale_elaboration_weighing/__init__.py
odoo/addons/sale_elaboration_weighing/__manifest__.py
odoo/addons/sale_elaboration_weighing/i18n/es.po
odoo/addons/sale_elaboration_weighing/i18n/sale_elaboration_weighing.pot
odoo/addons/sale_elaboration_weighing/models/__init__.py
odoo/addons/sale_elaboration_weighing/models/stock_move.py
odoo/addons/sale_elaboration_weighing/readme/CONTRIBUTORS.md
odoo/addons/sale_elaboration_weighing/readme/DESCRIPTION.md
odoo/addons/sale_elaboration_weighing/static/description/icon.png
odoo/addons/sale_elaboration_weighing/static/description/index.html
odoo/addons/sale_elaboration_weighing/static/src/scss/stock_weighing.scss
odoo/addons/sale_elaboration_weighing/views/stock_move_views.xml
odoo/addons/sale_elaboration_weighing/wizards/__init__.py
odoo/addons/sale_elaboration_weighing/wizards/weigh_operation_selection.py
odoo_addon_sale_elaboration_weighing-15.0.1.0.0.2.dist-info/METADATA
odoo_addon_sale_elaboration_weighing-15.0.1.0.0.2.dist-info/WHEEL
odoo_addon_sale_elaboration_weighing-15.0.1.0.0.2.dist-info/top_level.txt
odoo_addon_sale_elaboration_weighing-15.0.1.0.0.2.dist-info/RECORD
